MANIFEST.in
README.md
setup.py
cfg/matrix-bot.cfg.example
matrix_bot.egg-info/PKG-INFO
matrix_bot.egg-info/SOURCES.txt
matrix_bot.egg-info/dependency_links.txt
matrix_bot.egg-info/not-zip-safe
matrix_bot.egg-info/requires.txt
matrix_bot.egg-info/top_level.txt
matrixbot/__init__.py
matrixbot/ldap.py
matrixbot/matrix.py
matrixbot/utils.py
matrixbot/../cfg/matrix-bot.cfg.example
matrixbot/plugins/__init__.py
matrixbot/plugins/broadcast.py
matrixbot/plugins/feeder.py
matrixbot/plugins/trac.py
tools/matrix-bot
tools/matrix-subscriber