Metadata-Version: 1.1
Name: matrix-bot
Version: 0.15.3
Summary: A matrix.org bot
Home-page: http://github.com/psaavedra/matrix-bot
Author: Pablo Saavedra
Author-email: saavedra.pablo@gmail.com
License: MIT License
